{
  "generator-jhipster": {
    "authenticationType": "jwt",
    "cacheProvider": "caffeine",
    "clientFramework": "angularX",
    "serverPort": "8080",
    "serviceDiscoveryType": false,
    "skipUserManagement": false,
    "baseName": "jhipsterSampleApplication",
    "buildTool": "maven",
    "databaseType": "sql",
    "devDatabaseType": "h2Disk",
    "enableHibernateCache": true,
    "enableSwaggerCodegen": false,
    "enableTranslation": true,
    "jhiPrefix": "jhi",
    "languages": ["en", "fr"],
    "messageBroker": false,
    "nativeLanguage": "en",
    "prodDatabaseType": "mysql",
    "searchEngine": false,
    "skipClient": false,
    "testFrameworks": [],
    "websocket": false,
    "applicationType": "monolith",
    "packageName": "io.github.jhipster.sample",
    "packageFolder": "io/github/jhipster/sample",
    "jhipsterVersion": "6.10.5",
    "creationTimestamp": 1615538700592,
    "skipServer": false,
    "clientPackageManager": "npm",
    "clientTheme": "none",
    "clientThemeVariant": "",
    "useSass": true,
    "jwtSecretKey": "NWYyMDJmYTYzYTVmOWU1ZDI4ZGVlMTJmOTBiN2JlZDkwMjhlZWZmMjRlY2U3ZjEwZDdkN2MwN2E2MjI3ZDk1ZmFkMDVjMWUyYTIxNGM1OWJhZWU2ZDBiNzEwNjJkMGNhYmZjOWQ3NmUwOTE4NDMwN2QyYmIwMTUxYjllN2MyNTU=",
    "embeddableLaunchScript": false,
    "entitySuffix": "",
    "dtoSuffix": "DTO",
    "otherModules": [
      {
        "name": "generator-jhipster-quarkus",
        "version": "1.1.1"
      }
    ],
    "blueprints": [
      {
        "name": "generator-jhipster-quarkus",
        "version": "1.1.1"
      }
    ]
  },
  "entities": ["BankAccount", "Label", "Operation"]
}
